meepy/__init__.py
meepy-0.0.5.dist-info/LICENSE
meepy-0.0.5.dist-info/METADATA
meepy-0.0.5.dist-info/WHEEL
meepy-0.0.5.dist-info/top_level.txt
meepy-0.0.5.dist-info/RECORD
